Project/src/basic/basic.v
module and_g(
    a,
    b,
    c
);

input wire a, b;
output wire c;

assign c = a & b;
    
endmodule

module or_g(
    a,
    b,
    c
);

input wire a, b;
output wire c;

assign c = a | b;
    
endmodule

module xor_g(
    a,
    b,
    c
);

input wire a, b;
output wire c;

assign c = a ^ b;
    
endmodule

Project/src/one-bit-sub/onebit.v
`include "../basic/basic.v"

module onebit(
    a,
    b,
    bin,
    d,
    bout
);

input wire a, b, bin;
output d, bout;
wire xor_1_out, and_1_out, and_2_out;

xor_g XOR1(.a(a), .b(b), .c(xor_1_out));
xor_g XOR2(.a(bin), .b(xor_1_out), .c(d));

and_g AND1(.a(~a), .b(b), .c(and_1_out));
and_g AND2(.a(~xor_1_out), .b(bin), .c(and_2_out));

or_g OR1(.a(and_2_out), .b(and_1_out), .c(bout));

endmodule

Project/src/one-bit-sub/tb_onebit.v
`include "onebit.v"
module tb_onebit;

reg a, b, bin;
wire d, bout;

onebit uut(.a(a), .b(b), .bin(bin), .d(d), .bout(bout));

initial begin
  $dumpfile("tb_onebit.vcd");
  $dumpvars(0,tb_onebit);
end

initial begin
    $monitor("Time: %0t | a: %b | b: %h | bin: %h | d: %h | bout: %b",
            $time, a, b, bin, d, bout);

    a    = 0;
    b    = 0;
    bin  = 0;

    #1

    a    = 0;
    b    = 0;
    bin  = 1;

    #1

    a    = 0;
    b    = 1;
    bin  = 0;

    #1

    a    = 0;
    b    = 1;
    bin  = 1;

    #1

    a    = 1;
    b    = 0;
    bin  = 0;

    #1

    a    = 1;
    b    = 0;
    bin  = 1;

    #1

    a    = 1;
    b    = 1;
    bin  = 0;

    #1
    
    a    = 1;
    b    = 1;
    bin  = 1;

    #6

    $finish(2);
end

endmodule

Project/src/one-bit-sub/tb_onebit.vcd
$date
	Wed Dec 17 13:40:28 2025
$end
$version
	Icarus Verilog
$end
$timescale
	1s
$end
$scope module tb_onebit $end
$var wire 1 ! d $end
$var wire 1 " bout $end
$var reg 1 # a $end
$var reg 1 $ b $end
$var reg 1 % bin $end
$scope module uut $end
$var wire 1 # a $end
$var wire 1 $ b $end
$var wire 1 % bin $end
$var wire 1 & xor_1_out $end
$var wire 1 ! d $end
$var wire 1 " bout $end
$var wire 1 ' and_2_out $end
$var wire 1 ( and_1_out $end
$scope module AND1 $end
$var wire 1 ) a $end
$var wire 1 $ b $end
$var wire 1 ( c $end
$upscope $end
$scope module AND2 $end
$var wire 1 * a $end
$var wire 1 % b $end
$var wire 1 ' c $end
$upscope $end
$scope module OR1 $end
$var wire 1 ' a $end
$var wire 1 ( b $end
$var wire 1 " c $end
$upscope $end
$scope module XOR1 $end
$var wire 1 # a $end
$var wire 1 $ b $end
$var wire 1 & c $end
$upscope $end
$scope module XOR2 $end
$var wire 1 % a $end
$var wire 1 & b $end
$var wire 1 ! c $end
$upscope $end
$upscope $end
$upscope $end
$enddefinitions $end
$comment Show the parameter values. $end
$dumpall
$end
#0
$dumpvars
1*
1)
0(
0'
0&
0%
0$
0#
0"
0!
$end
#1
1"
1'
1!
1%
#2
0*
0'
1(
1&
0%
1$
#3
0!
1%
#4
0"
1!
0(
0)
0%
0$
1#
#5
0!
1%
#6
1*
0&
0%
1$
#7
1"
1'
1!
1%
