Exp9/P4/func.v
module func(
    f,
    x,
    y,
    z
);
  
  input wire x,y,z;
  output wire f;
  
  assign f = (x & y) | (~z);
  
endmodule

Exp9/P4/tb_func.v
module tb_func;
  
  reg x,y,z;
  wire f;
  
  func functionf(f,x,y,z);
  
  initial begin 
      $dumpfile("tb_func.vcd");
      $dumpvars(0,tb_func);
  end

  initial begin
    $monitor("Time: %0t | x: %h | y: %h | z: %h | f: %h",
                 $time, x, y, z, f);
    
    x = 0;
    y = 0;
    z = 0;

    #2

    x = 0;
    y = 0;
    z = 1;

    #2

    x = 0;
    y = 1;
    z = 0;

    #2

    x = 0;
    y = 1;
    z = 1;

    #2

    x = 1;
    y = 0;
    z = 0;

    #2

    x = 1;
    y = 0;
    z = 1;

    #2

    x = 1;
    y = 1;
    z = 0;

    #2

    x = 1;
    y = 1;
    z = 1;

    #2

    $finish(2);
  
  end

endmodule

Exp9/P4/tb_func.vcd
$date
	Mon Dec 15 10:23:57 2025
$end
$version
	Icarus Verilog
$end
$timescale
	1s
$end
$scope module tb_func $end
$var wire 1 ! f $end
$var reg 1 " x $end
$var reg 1 # y $end
$var reg 1 $ z $end
$scope module functionf $end
$var wire 1 ! f $end
$var wire 1 " x $end
$var wire 1 # y $end
$var wire 1 $ z $end
$upscope $end
$upscope $end
$enddefinitions $end
$comment Show the parameter values. $end
$dumpall
$end
#0
$dumpvars
0$
0#
0"
1!
$end
#2
0!
1$
#4
1!
0$
1#
#6
0!
1$
#8
1!
0$
0#
1"
#10
0!
1$
#12
1!
0$
1#
#14
1$
